jeugdjournaal/__init__.py
jeugdjournaal/jeugdjournaal.py
jeugdjournaal-0.1.9.dist-info/METADATA
jeugdjournaal-0.1.9.dist-info/WHEEL
jeugdjournaal-0.1.9.dist-info/top_level.txt
jeugdjournaal-0.1.9.dist-info/RECORD
