Metadata-Version: 2.1
Name: jeugdjournaal
Version: 0.1.9
Summary: Python library to interact with the jeugdjournaal API
Home-page: https://github.com/hcr5/jeugdjournaalpy
Author: hcr5
Author-email: hcr5.hcr@gmail.com
License: MIT
Classifier: Programming Language :: Python :: 3
Classifier: License :: OSI Approved :: MIT License
Classifier: Operating System :: OS Independent
Requires-Python: >=3.6
Requires-Dist: beautifulsoup4
Requires-Dist: requests
